{
    "home_paragraph": "Convinient Wines Italia specializes in supplying you with the best value for money Italian wines with a",
    "one_stop": "<b>One-Stop Solution</b>",
    "home_bullet_points": [
        {
            "id": 1,
            "point": "<b>One</b> order collection point"
        },
        {
            "id": 2,
            "point": "<b>One</b> invoice/administration"
        },
        {
            "id": 3,
            "point": "<b>One</b> contact person for everything"
        },
        {
            "id": 4,
            "point": "<b>One</b> comprehensive wine listing with over 100 varietals avaliable"
        }
    ],
    "home_service_text": "Convinient Wines Italia offers you a complete range of services and wine purchasing options covering all segmants of the wine market. Our experts will work to your brief and present to you all the best buying options avaliable, saving you time and money.",
    "home_service_picture": "/service-home.jpg",
    "home_wine_text": "some text about the wine page",
    "home_wine_picture": "/wine-bottle-blur.jpg",
    "about": "Convinient Wines Italia trades",
    "about_image" : "/small-logo-text-color.png",
    "services": [
        {
            "id": 1,
            "account_services": [
                {
                    "id": 1,
                    "service": "Your personal account manager"
                },
                {
                    "id": 2,
                    "service": "Single invoice"
                },
                {
                    "id": 3,
                    "service": "Single admin"
                },
                {
                    "id": 4,
                    "service": "Single logistics platform"
                }
            ]
        },
        {
            "id": 2,
            "language_services": [
                {
                    "id": 1,
                    "service": "Supply of Key Keg barrels"
                },
                {
                    "id": 2,
                    "service": "Supply of Bag-in-Box 3L and 5L"
                },
                {
                    "id": 3,
                    "service": "Production of your own private label"
                },
                {
                    "id": 4,
                    "service": "Fluent English speaking staff"
                }
            ],
            "picture": "/uk.png"
        },
        {
            "id": 3,
            "wine_services": [
                {
                    "id": 1,
                    "service": "Large Italian wine portfolio covering all the main regions"
                },
                {
                    "id": 2,
                    "service": "Wines from Entry level to International prize winners"
                },
                {
                    "id": 3,
                    "service": "Flexible ordering including mixed pallet selections"
                },
                {
                    "id": 4,
                    "service": "No MOQ's"
                }
            ]
        },
        {
            "id": 8,
            "service": "Flexable order quantities"
        },
        {
            "id": 9,
            "service": "Excellent price/quality delivery"
        },
        {
            "id": 10,
            "service": "Complete supply chain projects"
        },
        {
            "id": 11,
            "service": "Your private label project"
        }
    ]
}